binance_common/__init__.py
binance_common/configuration.py
binance_common/constants.py
binance_common/errors.py
binance_common/headers.py
binance_common/logger.py
binance_common/models.py
binance_common/signature.py
binance_common/utils.py
binance_common/websocket.py
binance_common-3.4.0.dist-info/METADATA
binance_common-3.4.0.dist-info/WHEEL
binance_common-3.4.0.dist-info/licenses/LICENCE
binance_common-3.4.0.dist-info/RECORD
